powell_opt-0.1.0.dist-info/METADATA
powell_opt-0.1.0.dist-info/WHEEL
powell_opt-0.1.0.dist-info/licenses/LICENSE
powell_opt/__init__.py
powell_opt/powell_opt.cpython-312-x86_64-linux-gnu.so
powell_opt-0.1.0.dist-info/RECORD
