Metadata-Version: 2.4
Name: powell-opt
Version: 0.1.0
Classifier: Intended Audience :: Science/Research
Classifier: License :: OSI Approved :: MIT License
Classifier: Programming Language :: Rust
Classifier: Programming Language :: Python :: Implementation :: CPython
Classifier: Programming Language :: Python :: Implementation :: PyPy
Classifier: Operating System :: OS Independent
Classifier: Programming Language :: Python :: 3
Classifier: Programming Language :: Python :: 3.9
Classifier: Programming Language :: Python :: 3.10
Classifier: Programming Language :: Python :: 3.11
Classifier: Programming Language :: Python :: 3.12
Classifier: Programming Language :: Python :: 3.13
Requires-Dist: maturin[patchelf]>=1.8.2 ; extra == 'dev'
Requires-Dist: pdm>=2.22.3 ; extra == 'dev'
Requires-Dist: pdm-bump>=0.9.10 ; extra == 'dev'
Requires-Dist: pre-commit>=4.1.0 ; extra == 'dev'
Requires-Dist: numpy>=1.20.0 ; extra == 'bench'
Requires-Dist: pytest>=8.3.5 ; extra == 'tests'
Provides-Extra: dev
Provides-Extra: bench
Provides-Extra: tests
License-File: LICENSE
Summary: Python bindings for the Powell method from scirs2-optimize
Keywords: optimization,powell,scientific,minimize
Author: Louis Maddox <louismmx@gmail.com>
Author-email: Louis Maddox <louismmx@gmail.com>
License: MIT
Requires-Python: >=3.9
Project-URL: Homepage, https://github.com/lmmx/powell-optimize
Project-URL: Repository, https://github.com/lmmx/powell-optimize.git
